time_rescale/__init__.py
time_rescale/core.py
time_rescale-0.2.2.dist-info/LICENSE
time_rescale-0.2.2.dist-info/METADATA
time_rescale-0.2.2.dist-info/WHEEL
time_rescale-0.2.2.dist-info/top_level.txt
time_rescale-0.2.2.dist-info/RECORD
