Metadata-Version: 2.1
Name: time-rescale
Version: 0.2.2
Summary: Tools for evaluating the goodness of fit of a pointprocess model via the time rescaling theorem
Home-page: https://github.com/Eden-Kramer-Lab/time_rescale
Author: Eric Denovellis
Author-email: eric.denovellis@ucsf.edu
License: MIT
Platform: UNKNOWN
License-File: LICENSE
Requires-Dist: numpy
Requires-Dist: scipy
Requires-Dist: matplotlib
